ncbi_genome_download/__init__.py
ncbi_genome_download/__main__.py
ncbi_genome_download/config.py
ncbi_genome_download/core.py
ncbi_genome_download/jobs.py
ncbi_genome_download/metadata.py
ncbi_genome_download/summary.py
ncbi_genome_download-0.3.3.data/scripts/gimme_taxa.py
ncbi_genome_download-0.3.3.dist-info/LICENSE
ncbi_genome_download-0.3.3.dist-info/METADATA
ncbi_genome_download-0.3.3.dist-info/WHEEL
ncbi_genome_download-0.3.3.dist-info/entry_points.txt
ncbi_genome_download-0.3.3.dist-info/top_level.txt
ncbi_genome_download-0.3.3.dist-info/RECORD
