Metadata-Version: 2.1
Name: ncbi-genome-download
Version: 0.3.3
Summary: Download genome files from the NCBI FTP server.
Home-page: https://github.com/kblin/ncbi-genome-download/
Author: Kai Blin
Author-email: kblin@biosustain.dtu.dk
License: Apache Software License
Classifier: Programming Language :: Python
Classifier: Programming Language :: Python :: 3
Classifier: Development Status :: 3 - Alpha
Classifier: Intended Audience :: Science/Research
Classifier: Topic :: Scientific/Engineering :: Bio-Informatics
Classifier: License :: OSI Approved :: Apache Software License
Classifier: Operating System :: OS Independent
Provides-Extra: testing
License-File: LICENSE
